[{"Section Type": "A1 College Requirement (3 credit units)", "Option List": [{"numberOf": 1, "classes": ["CMPT 140.3", "ECON 111.3", "ECON 114.3", "MATH 100.6", "MATH 101.3", "MATH 102.3", "MATH 104.3", "MATH 110.3", "MATH 121.3", "MATH 123.3", "MATH 125.3", "MATH 150.3", "MATH 163.3", "MATH 164.3", "MATH 176.3", "MATH 177.3", "STAT 103.3", "STAT 244.3", "STAT 246.3", "PHYS 115.3", "PSY 233.3", "SOC 225.3"], "info": []}]}, {"Section Type": "A2 Breadth Requirement (15 credit units)", "Option List": [{"numberOf": 3, "classes": ["ASTR 102.3", "ASTR 104.3", "ASTR 113.3", "BIOL 107.6", "BIOL 120.3", "BIOL 121.3", "CHEM 112.3", "CHEM 115.3", "CMPT 100.3", "CMPT 120.3", "CMPT 140.3", "CMPT 141.3", "CMPT 145.3", "GEOG 120.3", "GEOG 125.3", "GEOL 108.3", "GEOL 109.3", "GEOL 121.3", "GEOL 122.3", "MATH 104.3", "MATH 110.3", "MATH 116.3", "MATH 121.3", "MATH 125.3", "MATH 128.3", "MATH 163.3", "MATH 164.3", "MATH 176.3", "MATH 177.3", "PHYS 115.3", "PHYS 117.3 or PHYS 125.3", "STAT 103.3", "Any senior-level science course provided the prerequisite is met.", "MATH 102 and STAT 244 are not eligible to be used in this requirement.", "ANTH 111.3", "ARCH 112.3", "ARCH 116.3", "ECON 111.3", "ECON 114.3", "GEOG 130.3", "GEOG 150.3", "HLST 110.3", "INDG 107.3", "IS 110.3", "LING 111.3", "LING 112.3", "LING 113.3", "POLS 111.3", "POLS 112.3", "PSY 120.3", "PSY 121.3", "SOC 111.3", "SOC 112.3", "WGST 112.3", "Any senior-level social science course provided that the prerequisite is met.", "Statistics courses in social sciences are not\u00a0eligible for use in this requirement (e.g. PSY 233,\u00a0PSY 234,\u00a0SOC 225 and\u00a0SOC 325)."], "info": ""}, {"numberOf": 2, "classes": ["ART 110.3", "ART 111.6", "ART 112.6", "ART 136.3", "ART 141.3", "ART 151.3", "ART 152.3", "ART 161.3", "ARTH 120.3", "ARTH 121.3", "DRAM 101.3", "DRAM 104.6", "DRAM 108.3", "DRAM 110.3", "DRAM 111.3", "DRAM 113.3", "DRAM 118.3", "DRAM 119.3", "DRAM 121.3", "MUS 101.3", "MUS 105.3", "MUS 111.3", "MUS 120.2", "MUS 121.2", "MUS 125.1", "MUS 133.3", "MUS 134.3", "MUS 155.3", "MUS 156.3", "MUS 175.3", "MUS 184.3", "Any senior-level fine arts course provided that the prerequisite is met.", "ASTR 102.3", "ASTR 104.3", "ASTR 113.3", "BIOL 107.6", "BIOL 120.3", "BIOL 121.3", "CHEM 112.3", "CHEM 115.3", "CMPT 100.3", "CMPT 120.3", "CMPT 140.3", "CMPT 141.3", "CMPT 145.3", "GEOG 120.3", "GEOG 125.3", "GEOL 108.3", "GEOL 109.3", "GEOL 121.3", "GEOL 122.3", "MATH 104.3", "MATH 110.3", "MATH 116.3", "MATH 121.3", "MATH 125.3", "MATH 128.3", "MATH 163.3", "MATH 164.3", "MATH 176.3", "MATH 177.3", "PHYS 115.3", "PHYS 117.3 or PHYS 125.3", "STAT 103.3", "Any senior-level science course provided the prerequisite is met.", "MATH 102 and STAT 244 are not eligible to be used in this requirement.", "ANTH 111.3", "ARCH 112.3", "ARCH 116.3", "ECON 111.3", "ECON 114.3", "GEOG 130.3", "GEOG 150.3", "HLST 110.3", "INDG 107.3", "IS 110.3", "LING 111.3", "LING 112.3", "LING 113.3", "POLS 111.3", "POLS 112.3", "PSY 120.3", "PSY 121.3", "SOC 111.3", "SOC 112.3", "WGST 112.3", "Any senior-level social science course provided that the prerequisite is met.", "Statistics courses in social sciences are not\u00a0eligible for use in this requirement (e.g. PSY 233,\u00a0PSY 234,\u00a0SOC 225 and\u00a0SOC 325).", "INTS 110.3", "INTS 111.3", "INTS 112.3", "INTS 201.3", "INTS 203.3", "INTS 380.3"], "info": ""}]}, {"Section Type": "A3 Cognate Requirement (15 credit units)", "Option List": [{"numberOf": 5, "classes": ["ARBC 114.3", "ARBC 117.3", "CHIN 114.3", "CHIN 117.3", "CREE 101.6", "CREE 110.3", "CREE 120.6", "ESL 115.3", "ESL 116.3", "FREN 103.3", "FREN 106.3", "FREN 122.3", "FREN 125.3", "GERM 114.3", "GERM 117.3", "GRK 112.3", "GRK 113.3", "HEB 114.3", "HEB 117.3", "HNDI 114.3", "HNDI 117.3", "JPNS 114.3", "JPNS 117.3", "LATN 112.3", "LATN 113.3", "RUSS 114.3", "RUSS 117.3", "SNSK 114.3", "SNSK 117.3", "SPAN 114.3", "SPAN 117.3", "UKR 114.3", "UKR 117.3", "Any senior-level language course provided that the prerequisite is met."], "info": ""}]}, {"Section Type": "A4 Major Requirement (36 credit units)", "Option List": [{"numberOf": 2.0, "classes": ["100-Level\u00a0ENG Courses "], "info": []}, {"numberOf": 2.0, "classes": ["ENG 202.6", "ENG 203.6", "ENG 204.6", "ENG 290.6"], "info": []}, {"numberOf": 4.0, "classes": ["CMRS 333.3 (May be used to fulfill a Category 1 or Category 2 requirement, but not both)", "ENG 301.3", "ENG 310.3", "ENG 311.3", "ENG 312.3", "ENG 313.3", "ENG 314.3", "ENG 316.3", "ENG 402.3", "ENG 420.3"], "info": ["CMRS 333.3 (May be used to fulfill a Category 1 or Category 2 requirement, but not both)", "ENG 224.3", "ENG 225.3", "ENG 319.3", "ENG 322.3", "ENG 324.3", "ENG 326.3", "ENG 404.3", "ENG 406.3", "ENG 327.3 ", "ENG 331.3", "ENG 334.3", "ENG 335.3", "ENG 340.3", "ENG 341.3", "ENG 362.3", "ENG 373.3", "ENG 380.3", "ENG 410.3", "ENG 414.3", "ENG 416.3", "ENG 418.3"]}, {"numberOf": 4.0, "classes": ["ENG \u2014 200-Level, 300-Level, 400-Level"], "info": []}, {"numberOf": 5.0, "classes": ["ENG 254.3", "ENG 255.3", "ENG 294.3", "ENG 305.3", "ENG 338.3", "ENG 358.3", "ENG 359.3", "ENG 382.3", "ENG 418.3", "ENG 466.3"], "info": []}]}, {"Section Type": "A5 Electives Requirement (51 credit units)", "Option List": [{"numberOf": 17.0, "classes": "any", "info": []}]}]